mockspace/__init__.py
mockspace/auth.py
mockspace/backup_service.py
mockspace/db.py
mockspace/methods.py
mockspace/schema.sql
mockspace/service.py
mockspace/services.py
mockspace/start_server.py
mockspace/static/style_dark_theme.css
mockspace/static/style_light_theme.css
mockspace/templates/base.html
mockspace/templates/base_addedit.html
mockspace/templates/auth/login.html
mockspace/templates/auth/register.html
mockspace/templates/method/create_method.html
mockspace/templates/method/method_not_allowed.html
mockspace/templates/method/services.html
mockspace/templates/method/update_method.html
mockspace/templates/service/backup_index.html
mockspace/templates/service/create.html
mockspace/templates/service/create_method.html
mockspace/templates/service/create_method_backup.html
mockspace/templates/service/index.html
mockspace/templates/service/method_not_allowed.html
mockspace/templates/service/service.html
mockspace/templates/service/services.html
mockspace/templates/service/update.html
mockspace/templates/service/update_method.html
mockspace-0.1.4.dist-info/LICENSE
mockspace-0.1.4.dist-info/METADATA
mockspace-0.1.4.dist-info/WHEEL
mockspace-0.1.4.dist-info/entry_points.txt
mockspace-0.1.4.dist-info/top_level.txt
mockspace-0.1.4.dist-info/RECORD
