Metadata-Version: 2.1
Name: mockspace
Version: 0.1.4
Summary: A convenient tool for quickly creating a mock environment: add web-services, fill them with the methods you need, configure response parameters
Home-page: https://mockspace.io
Author: mockspace team
License: MIT
Project-URL: Source, https://github.com/mockspace/mockspace
Platform: UNKNOWN
Classifier: Development Status :: 4 - Beta
Classifier: Programming Language :: Python :: 3
Classifier: License :: OSI Approved :: MIT License
Requires-Python: >=3.6
Requires-Dist: flask
Requires-Dist: waitress
Provides-Extra: test
Requires-Dist: pytest ; extra == 'test'
Requires-Dist: coverage ; extra == 'test'
